FaspaySendme/Api.py
FaspaySendme/__init__.py
FaspaySendme/_http.py
FaspaySendme/_request.py
FaspaySendme-1.5.dist-info/METADATA
FaspaySendme-1.5.dist-info/WHEEL
FaspaySendme-1.5.dist-info/top_level.txt
FaspaySendme-1.5.dist-info/RECORD
