Metadata-Version: 2.1
Name: FaspaySendme
Version: 1.5
Summary: This package provides Faspay SendMe 1.5 support for the Python Language.
Home-page: https://github.com/faspay-team/faspay-sendme-python
Author: Vincentius Setyo K
Author-email: vincentius.setyo@faspay.co.id
License: MIT
Platform: UNKNOWN
